pytest_repeat.py
pytest_repeat-0.9.2.dist-info/LICENSE
pytest_repeat-0.9.2.dist-info/METADATA
pytest_repeat-0.9.2.dist-info/WHEEL
pytest_repeat-0.9.2.dist-info/entry_points.txt
pytest_repeat-0.9.2.dist-info/top_level.txt
pytest_repeat-0.9.2.dist-info/RECORD
